enhancesa/__init__.py
enhancesa/_version.py
enhancesa/bootstrap.py
enhancesa/command_line.py
enhancesa/diag_plots.py
enhancesa/subset_selection.py
enhancesa/subset_selection/__init__.py
enhancesa/subset_selection/backward_select.py
enhancesa/subset_selection/best_subset.py
enhancesa/subset_selection/forward_select.py
enhancesa-0.1a0.data/data/LICENSE.txt
enhancesa-0.1a0.data/data/setup.cfg
enhancesa-0.1a0.data/scripts/enhancesa
tests/__init__.py
tests/test_bootstrap.py
tests/test_diag_plots.py
tests/test_hello.py
tests/test_subset_select.py
enhancesa-0.1a0.dist-info/LICENSE.txt
enhancesa-0.1a0.dist-info/METADATA
enhancesa-0.1a0.dist-info/WHEEL
enhancesa-0.1a0.dist-info/entry_points.txt
enhancesa-0.1a0.dist-info/top_level.txt
enhancesa-0.1a0.dist-info/RECORD
