Metadata-Version: 2.1
Name: enhancesa
Version: 0.1a0
Summary: Python micro-package for enhanced statistical analysis
Home-page: https://github.com/alisiina/enhancesa
Author: Ali Sina
Author-email: alisina47@gmail.com
License: MIT
Project-URL: Documentation, https://enhancesa.readthedocs.io/en/latest/?badge=latest
Project-URL: Say Thanks!, https://saythanks.io/to/alisiina
Project-URL: Source, https://github.com/alisiina/enhancesa/
Project-URL: Tracker, https://github.com/alisiina/enhancesa/issues
Keywords: statistics mathematics plotting diagnostics analysis
Platform: UNKNOWN
Classifier: Development Status :: 2 - Pre-Alpha
Classifier: License :: OSI Approved :: MIT License
Classifier: Programming Language :: Python :: 3.5
Classifier: Programming Language :: Python :: 3.6
Classifier: Programming Language :: Python :: 3.7
Classifier: Framework :: IPython
Classifier: Intended Audience :: Science/Research
Classifier: Topic :: Scientific/Engineering :: Visualization
Requires-Python: >=3.6
Requires-Dist: matplotlib (>=3.0.2)
Requires-Dist: statsmodels (>=0.9.0)
Requires-Dist: seaborn (>=0.9.0)
Requires-Dist: numpy (>=1.15.4)
Requires-Dist: pandas (>=0.24.0)
Requires-Dist: tqdm (>=4.28.1)
